<Footprint name="zhongzhou" >
 <Units type="millimeters" precision="4" />
 <Extents minX="-19.5200" minY="-19.2400" width="39.0400" height="39.0400" />
 <Padstack name="c147h87t127_157" type="through-hole" > 
   <Hole plating="plated" >
    <Drill figure="Circle" diameter="0.8774" width="0.8774" height="0.8774" />
   </Hole>
  <Shapes>
  </Shapes>
   <Layers>
    <Layer name="TOP" >
     <Pad shape="circle" width="1.4774" height="1.4774" />
    </Layer>
    <Layer name="default_internal" >
     <Pad shape="circle" width="1.4774" height="1.4774" />
    </Layer>
    <Layer name="BOTTOM" >
     <Pad shape="circle" width="1.4774" height="1.4774" />
    </Layer>
    <Layer name="SOLDERMASK_TOP" >
     <Pad shape="circle" width="1.4774" height="1.4774" />
    </Layer>
    <Layer name="SOLDERMASK_BOTTOM" >
     <Pad shape="circle" width="1.4774" height="1.4774" />
    </Layer>
   </Layers>
 </Padstack>
 <Padstack name="s147h87t127_157" type="through-hole" > 
   <Hole plating="plated" >
    <Drill figure="Circle" diameter="0.8774" width="0.8774" height="0.8774" />
   </Hole>
  <Shapes>
  </Shapes>
   <Layers>
    <Layer name="TOP" >
     <Pad shape="square" width="1.4774" height="1.4774" />
    </Layer>
    <Layer name="default_internal" >
     <Pad shape="circle" width="1.4774" height="1.4774" />
    </Layer>
    <Layer name="BOTTOM" >
     <Pad shape="square" width="1.4774" height="1.4774" />
    </Layer>
    <Layer name="SOLDERMASK_TOP" >
     <Pad shape="square" width="1.4774" height="1.4774" />
    </Layer>
    <Layer name="SOLDERMASK_BOTTOM" >
     <Pad shape="square" width="1.4774" height="1.4774" />
    </Layer>
   </Layers>
 </Padstack>
 <Pins>
  <Pin number="1" padName="s147h87t127_157" originX="-2.2500" originY="2.2500" rotation="0" isMechanical="no" textBlk="1" />
  <Pin number="2" padName="c147h87t127_157" originX="-2.2500" originY="0.0000" rotation="0" isMechanical="no" textBlk="1" />
  <Pin number="3" padName="c147h87t127_157" originX="-2.2500" originY="-2.2500" rotation="0" isMechanical="no" textBlk="1" />
  <Pin number="4" padName="c147h87t127_157" originX="2.2500" originY="-2.2500" rotation="180" isMechanical="no" textBlk="1" />
  <Pin number="5" padName="c147h87t127_157" originX="2.2500" originY="0.0000" rotation="180" isMechanical="no" textBlk="1" />
  <Pin number="6" padName="c147h87t127_157" originX="2.2500" originY="2.2500" rotation="180" isMechanical="no" textBlk="1" />
 </Pins>
 <Vias>
 </Vias>
 <Layers>
  <Layer name="PACKAGE GEOMETRY/ASSEMBLY_TOP" packageHeight="5.3300" >
   <Path lineWidth="0.1000" type="line" >
    <Point x="-4.0000" y="-4.0000" />
    <Point x="-4.0000" y="4.0000" />
    <Point x="4.0000" y="4.0000" />
    <Point x="4.0000" y="-4.0000" />
    <Point x="-4.0000" y="-4.0000" />
   </Path>
   <Label layer="REF DES/ASSEMBLY_TOP" textBlock="3" angle="0" x="0.0000" y="-0.6750" text="Ref" />
   <Circle type="line" lineWidth="0.1000" originX="-0.5113" originY="3.0000" radius="0.5000" />
  </Layer>
  <Layer name="PACKAGE GEOMETRY/SILKSCREEN_TOP" packageHeight="5.3300" >
   <Path lineWidth="0.2000" type="line" >
    <Point x="-1.1613" y="-4.0000" />
    <Point x="-1.1613" y="4.0000" />
    <Point x="1.1613" y="4.0000" />
    <Point x="1.1613" y="-4.0000" />
    <Point x="-1.1613" y="-4.0000" />
   </Path>
   <Label layer="REF DES/SILKSCREEN_TOP" textBlock="3" angle="0" x="0.0000" y="4.2750" text="Ref" />
   <Label layer="DEVICE TYPE/SILKSCREEN_TOP" textBlock="3" angle="0" x="0.0000" y="3.8250" text="Dev" />
   <Circle type="shape" lineWidth="0.2000" originX="-0.3613" originY="3.2000" radius="0.4000" />
  </Layer>
  <Layer name="PACKAGE GEOMETRY/PLACE_BOUND_TOP" packageHeight="5.3300" >
   <Path lineWidth="0.0500" type="shape" >
    <Point x="-4.2500" y="-4.2500" />
    <Point x="-4.2500" y="4.2500" />
    <Point x="4.2500" y="4.2500" />
    <Point x="4.2500" y="-4.2500" />
    <Point x="-4.2500" y="-4.2500" />
   </Path>
  </Layer>
  <Layer name="PACKAGE GEOMETRY/DFA_BOUND_TOP" packageHeight="5.3300" >
   <Path lineWidth="0.0000" type="shape" >
    <Point x="-4.2500" y="-4.2500" />
    <Point x="-4.2500" y="4.2500" />
    <Point x="4.2500" y="4.2500" />
    <Point x="4.2500" y="-4.2500" />
    <Point x="-4.2500" y="-4.2500" />
   </Path>
  </Layer>
  <Layer name="MANUFACTURING/NO_PROBE_TOP" packageHeight="5.3300" >
   <Path lineWidth="0.0000" type="shape" >
    <Point x="-4.2500" y="-4.2500" />
    <Point x="-4.2500" y="4.2500" />
    <Point x="4.2500" y="4.2500" />
    <Point x="4.2500" y="-4.2500" />
    <Point x="-4.2500" y="-4.2500" />
   </Path>
  </Layer>
 </Layers>
</Footprint>
